{
  "person_to_branchplanset": {
    "@maxbachmann": {
      "branches": [
        {
          "name": "feature/weighted-edits",
          "rationale": "To enhance similarity scoring by allowing certain character substitutions to count differently in edit distance calculations.",
          "tasks_included": [
            "task_1"
          ],
          "parts_covered": {
            "src/Levenshtein": [
              "levenshtein_cpp.pyx",
              "__init__.py"
            ],
            "docs": [
              "levenshtein.rst"
            ],
            "tests": [
              "test_levenshtein_distance.py"
            ]
          },
          "risk_notes": [],
          "commits": [
            {
              "title": "Add distance_with_weights method",
              "body": "Implemented the distance_with_weights method to support weighted edits in distance calculations.",
              "files": [
                "src/Levenshtein/levenshtein_cpp.pyx"
              ],
              "per_file_changes": [
                "Added distance_with_weights method to calculate edit distance with weights."
              ]
            },
            {
              "title": "Update documentation for weighted edits",
              "body": "Updated the documentation to include the new distance_with_weights method and its usage.",
              "files": [
                "docs/levenshtein.rst"
              ],
              "per_file_changes": [
                "Added documentation for distance_with_weights method."
              ]
            },
            {
              "title": "Add tests for weighted edits",
              "body": "Created tests to validate the behavior of the distance_with_weights method.",
              "files": [
                "tests/test_levenshtein_distance.py"
              ],
              "per_file_changes": [
                "Added test cases for distance_with_weights method."
              ]
            }
          ]
        },
        {
          "name": "feature/max-distance-cutoff",
          "rationale": "To improve performance by allowing the distance method to return early for inputs exceeding a specified threshold.",
          "tasks_included": [
            "task_2"
          ],
          "parts_covered": {
            "src/Levenshtein": [
              "levenshtein_cpp.pyx",
              "__init__.py"
            ],
            "tests": [
              "test_levenshtein_distance.py"
            ]
          },
          "risk_notes": [],
          "commits": [
            {
              "title": "Implement max distance cutoff in distance method",
              "body": "Added max_dist parameter to distance method to allow early returns for large distances.",
              "files": [
                "src/Levenshtein/levenshtein_cpp.pyx"
              ],
              "per_file_changes": [
                "Modified distance method to include max_dist parameter."
              ]
            },
            {
              "title": "Update tests for max distance cutoff",
              "body": "Added tests to ensure the max_dist functionality works as expected.",
              "files": [
                "tests/test_levenshtein_distance.py"
              ],
              "per_file_changes": [
                "Added test cases for max distance cutoff."
              ]
            }
          ]
        }
      ]
    },
    "@guyrosin": {
      "branches": [
        {
          "name": "feature/multi-threaded-batch",
          "rationale": "To allow faster processing of large lists of strings for similarity ranking through parallel computation.",
          "tasks_included": [
            "task_3"
          ],
          "parts_covered": {
            "src/Levenshtein": [
              "levenshtein_cpp.pyx",
              "__init__.py"
            ],
            "tests": [
              "test_levenshtein_distance.py"
            ]
          },
          "risk_notes": [],
          "commits": [
            {
              "title": "Add batch_distance method for multi-threading",
              "body": "Implemented batch_distance method to compute distances in parallel.",
              "files": [
                "src/Levenshtein/levenshtein_cpp.pyx"
              ],
              "per_file_changes": [
                "Added batch_distance method for multi-threaded computation."
              ]
            },
            {
              "title": "Update documentation for batch processing",
              "body": "Updated documentation to include the new batch_distance method.",
              "files": [
                "docs/levenshtein.rst"
              ],
              "per_file_changes": [
                "Added documentation for batch_distance method."
              ]
            },
            {
              "title": "Add performance tests for batch processing",
              "body": "Created performance tests to validate the efficiency of the batch_distance method.",
              "files": [
                "tests/test_levenshtein_distance.py"
              ],
              "per_file_changes": [
                "Added performance test cases for batch_distance method."
              ]
            }
          ]
        },
        {
          "name": "feature/edit-operations-path",
          "rationale": "To provide detailed insights into the edit operations performed during distance calculations.",
          "tasks_included": [
            "task_4"
          ],
          "parts_covered": {
            "src/Levenshtein": [
              "levenshtein_cpp.pyx",
              "__init__.py"
            ],
            "tests": [
              "test_levenshtein_distance.py"
            ]
          },
          "risk_notes": [],
          "commits": [
            {
              "title": "Add distance_with_ops method",
              "body": "Implemented distance_with_ops method to return edit operations.",
              "files": [
                "src/Levenshtein/levenshtein_cpp.pyx"
              ],
              "per_file_changes": [
                "Added distance_with_ops method to return edit operations."
              ]
            },
            {
              "title": "Update documentation for edit operations",
              "body": "Updated documentation to include the new distance_with_ops method.",
              "files": [
                "docs/levenshtein.rst"
              ],
              "per_file_changes": [
                "Added documentation for distance_with_ops method."
              ]
            },
            {
              "title": "Add tests for edit operations",
              "body": "Created tests to validate the behavior of the distance_with_ops method.",
              "files": [
                "tests/test_levenshtein_distance.py"
              ],
              "per_file_changes": [
                "Added test cases for distance_with_ops method."
              ]
            }
          ]
        }
      ]
    },
    "@antoinetavant": {
      "branches": [
        {
          "name": "feature/unicode-grapheme-clusters",
          "rationale": "To ensure multi-codepoint characters are treated as single units in distance calculations, improving correctness.",
          "tasks_included": [
            "task_5"
          ],
          "parts_covered": {
            "src/Levenshtein": [
              "levenshtein_cpp.pyx",
              "__init__.py"
            ],
            "tests": [
              "test_levenshtein_distance.py"
            ]
          },
          "risk_notes": [],
          "commits": [
            {
              "title": "Add support for grapheme clusters",
              "body": "Implemented support for grapheme clusters in distance calculations.",
              "files": [
                "src/Levenshtein/levenshtein_cpp.pyx"
              ],
              "per_file_changes": [
                "Modified distance methods to handle grapheme clusters."
              ]
            },
            {
              "title": "Update documentation for grapheme support",
              "body": "Updated documentation to reflect the new grapheme cluster support.",
              "files": [
                "docs/levenshtein.rst"
              ],
              "per_file_changes": [
                "Added documentation for grapheme cluster support."
              ]
            },
            {
              "title": "Add tests for grapheme clusters",
              "body": "Created tests to validate the behavior of distance methods with grapheme clusters.",
              "files": [
                "tests/test_levenshtein_distance.py"
              ],
              "per_file_changes": [
                "Added test cases for grapheme cluster handling."
              ]
            }
          ]
        }
      ]
    },
    "@LecrisUT": {
      "branches": [
        {
          "name": "feature/pure-python-fallback",
          "rationale": "To maintain functionality on platforms where the C extension cannot compile, enhancing portability.",
          "tasks_included": [
            "task_6"
          ],
          "parts_covered": {
            "src/Levenshtein": [
              "levenshtein_py.dart"
            ],
            "tests": [
              "test_levenshtein_distance.py"
            ]
          },
          "risk_notes": [],
          "commits": [
            {
              "title": "Add pure-Python fallback module",
              "body": "Implemented levenshtein_py.dart as a fallback for C extension.",
              "files": [
                "src/Levenshtein/levenshtein_py.dart"
              ],
              "per_file_changes": [
                "Added pure-Python implementation for Levenshtein distance."
              ]
            },
            {
              "title": "Update selection logic for fallback",
              "body": "Implemented logic to select between C extension and pure-Python fallback.",
              "files": [
                "src/Levenshtein/__init__.py"
              ],
              "per_file_changes": [
                "Added logic to choose between C extension and pure-Python fallback."
              ]
            },
            {
              "title": "Update documentation for fallback module",
              "body": "Updated documentation to include information about the pure-Python fallback.",
              "files": [
                "docs/levenshtein.rst"
              ],
              "per_file_changes": [
                "Added documentation for pure-Python fallback module."
              ]
            },
            {
              "title": "Add tests for fallback module",
              "body": "Created tests to validate the behavior of the pure-Python fallback.",
              "files": [
                "tests/test_levenshtein_distance.py"
              ],
              "per_file_changes": [
                "Added test cases for pure-Python fallback module."
              ]
            }
          ]
        }
      ]
    },
    "@eansengchang": {
      "branches": [
        {
          "name": "docs/readme-review-note",
          "rationale": "To add a simple line in readme file that says 'reviewed by Bob'.",
          "tasks_included": [
            "task_7"
          ],
          "parts_covered": {
            "README.md": [
              "Add 'reviewed by Bob' line"
            ]
          },
          "risk_notes": [],
          "commits": [
            {
              "title": "Docs: Add review acknowledgement",
              "body": "Added 'reviewed by Bob' line to README.",
              "files": [
                "README.md"
              ],
              "per_file_changes": [
                "Added 'reviewed by Bob' line"
              ]
            }
          ]
        }
      ]
    }
  }
}